and_project/__init__.py
and_project/andy.py
and_project-0.3.0.dist-info/METADATA
and_project-0.3.0.dist-info/WHEEL
and_project-0.3.0.dist-info/entry_points.txt
and_project-0.3.0.dist-info/RECORD
