Metadata-Version: 2.1
Name: and-project
Version: 0.3.0
Summary: En test
Author: AndreasB
Requires-Python: >=3.11,<4.0
Classifier: Programming Language :: Python :: 3
Classifier: Programming Language :: Python :: 3.11
Classifier: Programming Language :: Python :: 3.12
